mahilo/__init__.py
mahilo/agent.py
mahilo/agent_manager.py
mahilo/cli.py
mahilo/client.py
mahilo/orchestrator_team.py
mahilo/registry.py
mahilo/server.py
mahilo/session.py
mahilo/tools.py
mahilo/integrations/langgraph/agent.py
mahilo/integrations/langgraph/tools.py
mahilo/integrations/pydanticai/agent.py
mahilo/integrations/pydanticai/tools.py
mahilo/templates/__init__.py
mahilo/templates/centralized/__init__.py
mahilo/templates/centralized/dispatcher.py
mahilo/templates/centralized/mold_specialist.py
mahilo/templates/centralized/plumber.py
mahilo/templates/peer2peer/__init__.py
mahilo/templates/peer2peer/logistics_coordinator.py
mahilo/templates/peer2peer/medical_advisor.py
mahilo/templates/peer2peer/public_communications_director.py
mahilo-0.4.2.dist-info/LICENSE
mahilo-0.4.2.dist-info/METADATA
mahilo-0.4.2.dist-info/WHEEL
mahilo-0.4.2.dist-info/entry_points.txt
mahilo-0.4.2.dist-info/top_level.txt
mahilo-0.4.2.dist-info/RECORD
