Metadata-Version: 2.2
Name: mahilo
Version: 0.4.2
Summary:  A flexible framework for creating multi-agent systems that can each interact with humans while sharing relevant context internally.
Author-email: Jayesh Sharma <wjayesh@outlook.com>
Project-URL: Homepage, https://github.com/wjayesh/mahilo
Requires-Python: >=3.9
License-File: LICENSE
Requires-Dist: openai<2.0.0,>=1.55.0
Requires-Dist: fastapi<0.115.6,>=0.109.2
Requires-Dist: uvicorn
Requires-Dist: websockets
Requires-Dist: python-dotenv
Requires-Dist: pydantic
Requires-Dist: rich
Requires-Dist: langgraph<0.3.0,>=0.2.60
Requires-Dist: pydantic-ai<0.1.0,>=0.0.15
Provides-Extra: voice
Requires-Dist: pyaudio; extra == "voice"
